digrdf/__init__.py
digrdf/__main__.py
digrdf/core.py
digrdf/instance_query.sparql
digrdf/prefixes.py
digrdf/schema_query.sparql
digrdf-0.1.8.dist-info/METADATA
digrdf-0.1.8.dist-info/WHEEL
digrdf-0.1.8.dist-info/RECORD
