Metadata-Version: 2.1
Name: digrdf
Version: 0.1.8
Summary: RDF Schema Diagram creation tool
Author: Lawson Lewis
Author-email: lawson@kurrawong.ai
Requires-Python: >=3.11,<4.0
Classifier: Programming Language :: Python :: 3
Classifier: Programming Language :: Python :: 3.11
Classifier: Programming Language :: Python :: 3.12
Requires-Dist: pyvis (>=0.3.2,<0.4.0)
Requires-Dist: requests (>=2.31.0,<3.0.0)
